anstu_sign_up-1.1.1.data/data/.template
anstu_sign_up-1.1.1.data/data/README.md
anstu_sign_up-1.1.1.data/data/help.txt
anstu_sign_up-1.1.1.data/data/sign_up.cmd
signup/__init__.py
signup/_config.py
signup/info.py
signup/login.py
signup/main.py
signup/temperature.py
signup/utils.py
anstu_sign_up-1.1.1.dist-info/LICENSE
anstu_sign_up-1.1.1.dist-info/METADATA
anstu_sign_up-1.1.1.dist-info/WHEEL
anstu_sign_up-1.1.1.dist-info/entry_points.txt
anstu_sign_up-1.1.1.dist-info/top_level.txt
anstu_sign_up-1.1.1.dist-info/RECORD
