Metadata-Version: 2.1
Name: anstu-sign-up
Version: 1.1.1
Summary: a simple script to deal with daily sign-up in AHSTU
Home-page: https://github.com/NoSimpleApple/ahstu_sign_up
Author: uncle_hoshino
Author-email: hgenaaaa@gmail.com
License: MIT
Classifier: Programming Language :: Python :: 3
Classifier: License :: OSI Approved :: MIT License
Classifier: Natural Language :: English
Requires-Python: >=3.10
License-File: LICENSE
